{
 "stock": "3045.TW",
 "name": "台灣大",
 "price": 118.0,
 "change_pct": 0.85,
 "ohlc": [
  {
   "time": "2026-03-16",
   "o": 107.0,
   "h": 108.0,
   "l": 107.0,
   "c": 108.0,
   "v": 6205788
  },
  {
   "time": "2026-03-17",
   "o": 108.5,
   "h": 109.5,
   "l": 108.0,
   "c": 109.5,
   "v": 9779626
  },
  {
   "time": "2026-03-18",
   "o": 109.5,
   "h": 110.0,
   "l": 108.5,
   "c": 110.0,
   "v": 12331048
  },
  {
   "time": "2026-03-19",
   "o": 109.5,
   "h": 109.5,
   "l": 108.5,
   "c": 109.5,
   "v": 5108785
  },
  {
   "time": "2026-03-20",
   "o": 109.0,
   "h": 109.5,
   "l": 108.5,
   "c": 109.0,
   "v": 5671532
  },
  {
   "time": "2026-03-23",
   "o": 108.0,
   "h": 109.5,
   "l": 108.0,
   "c": 109.0,
   "v": 8033228
  },
  {
   "time": "2026-03-24",
   "o": 109.0,
   "h": 110.0,
   "l": 109.0,
   "c": 109.5,
   "v": 6427056
  },
  {
   "time": "2026-03-25",
   "o": 109.5,
   "h": 110.0,
   "l": 109.0,
   "c": 109.0,
   "v": 8432055
  },
  {
   "time": "2026-03-26",
   "o": 109.5,
   "h": 109.5,
   "l": 109.0,
   "c": 109.0,
   "v": 3427403
  },
  {
   "time": "2026-03-27",
   "o": 109.0,
   "h": 109.5,
   "l": 108.5,
   "c": 109.5,
   "v": 4945614
  },
  {
   "time": "2026-03-30",
   "o": 108.5,
   "h": 110.0,
   "l": 108.5,
   "c": 109.0,
   "v": 7569588
  },
  {
   "time": "2026-03-31",
   "o": 109.0,
   "h": 109.5,
   "l": 108.5,
   "c": 109.0,
   "v": 7711771
  },
  {
   "time": "2026-04-01",
   "o": 109.0,
   "h": 109.5,
   "l": 108.5,
   "c": 109.5,
   "v": 4617098
  },
  {
   "time": "2026-04-02",
   "o": 109.5,
   "h": 109.5,
   "l": 109.0,
   "c": 109.5,
   "v": 5662131
  },
  {
   "time": "2026-04-07",
   "o": 109.5,
   "h": 109.5,
   "l": 109.0,
   "c": 109.5,
   "v": 4621281
  },
  {
   "time": "2026-04-08",
   "o": 109.5,
   "h": 109.5,
   "l": 108.5,
   "c": 109.5,
   "v": 7373153
  },
  {
   "time": "2026-04-09",
   "o": 109.5,
   "h": 110.0,
   "l": 109.0,
   "c": 110.0,
   "v": 8222656
  },
  {
   "time": "2026-04-10",
   "o": 110.0,
   "h": 110.0,
   "l": 109.5,
   "c": 110.0,
   "v": 5146145
  },
  {
   "time": "2026-04-13",
   "o": 110.0,
   "h": 110.0,
   "l": 109.5,
   "c": 110.0,
   "v": 6910407
  },
  {
   "time": "2026-04-14",
   "o": 110.0,
   "h": 110.0,
   "l": 109.5,
   "c": 110.0,
   "v": 7058852
  },
  {
   "time": "2026-04-15",
   "o": 110.0,
   "h": 110.0,
   "l": 109.5,
   "c": 110.0,
   "v": 7559256
  },
  {
   "time": "2026-04-16",
   "o": 110.0,
   "h": 110.0,
   "l": 109.5,
   "c": 110.0,
   "v": 7835526
  },
  {
   "time": "2026-04-17",
   "o": 110.0,
   "h": 112.5,
   "l": 109.5,
   "c": 112.5,
   "v": 19081336
  },
  {
   "time": "2026-04-20",
   "o": 112.5,
   "h": 115.5,
   "l": 112.0,
   "c": 113.5,
   "v": 24209816
  },
  {
   "time": "2026-04-21",
   "o": 113.5,
   "h": 114.0,
   "l": 112.0,
   "c": 113.5,
   "v": 18916165
  },
  {
   "time": "2026-04-22",
   "o": 113.5,
   "h": 113.5,
   "l": 111.5,
   "c": 113.0,
   "v": 13599233
  },
  {
   "time": "2026-04-23",
   "o": 112.0,
   "h": 112.5,
   "l": 111.0,
   "c": 112.0,
   "v": 11097887
  },
  {
   "time": "2026-04-24",
   "o": 112.0,
   "h": 113.5,
   "l": 111.5,
   "c": 113.0,
   "v": 22379836
  },
  {
   "time": "2026-04-27",
   "o": 112.5,
   "h": 113.0,
   "l": 112.0,
   "c": 112.0,
   "v": 8103524
  },
  {
   "time": "2026-04-28",
   "o": 112.5,
   "h": 112.5,
   "l": 111.0,
   "c": 111.0,
   "v": 8844392
  },
  {
   "time": "2026-04-29",
   "o": 111.0,
   "h": 112.0,
   "l": 111.0,
   "c": 112.0,
   "v": 11316518
  },
  {
   "time": "2026-04-30",
   "o": 111.5,
   "h": 112.0,
   "l": 111.0,
   "c": 111.5,
   "v": 7757957
  },
  {
   "time": "2026-05-04",
   "o": 111.5,
   "h": 111.5,
   "l": 110.5,
   "c": 110.5,
   "v": 7397198
  },
  {
   "time": "2026-05-05",
   "o": 110.5,
   "h": 111.0,
   "l": 110.0,
   "c": 110.5,
   "v": 10644849
  },
  {
   "time": "2026-05-06",
   "o": 110.5,
   "h": 110.5,
   "l": 110.0,
   "c": 110.0,
   "v": 5464743
  },
  {
   "time": "2026-05-07",
   "o": 110.5,
   "h": 110.5,
   "l": 110.0,
   "c": 110.0,
   "v": 6180572
  },
  {
   "time": "2026-05-08",
   "o": 110.0,
   "h": 110.5,
   "l": 109.5,
   "c": 110.0,
   "v": 7853369
  },
  {
   "time": "2026-05-11",
   "o": 110.0,
   "h": 110.5,
   "l": 109.5,
   "c": 110.0,
   "v": 7486422
  },
  {
   "time": "2026-05-12",
   "o": 110.0,
   "h": 110.5,
   "l": 110.0,
   "c": 110.0,
   "v": 5392541
  },
  {
   "time": "2026-05-13",
   "o": 110.0,
   "h": 113.0,
   "l": 109.5,
   "c": 112.0,
   "v": 20204286
  },
  {
   "time": "2026-05-14",
   "o": 111.5,
   "h": 115.0,
   "l": 111.5,
   "c": 115.0,
   "v": 20297382
  },
  {
   "time": "2026-05-15",
   "o": 115.0,
   "h": 115.5,
   "l": 114.5,
   "c": 114.5,
   "v": 12686599
  },
  {
   "time": "2026-05-18",
   "o": 114.5,
   "h": 115.5,
   "l": 114.0,
   "c": 114.0,
   "v": 12828566
  },
  {
   "time": "2026-05-19",
   "o": 114.0,
   "h": 117.5,
   "l": 113.5,
   "c": 116.5,
   "v": 26364727
  },
  {
   "time": "2026-05-20",
   "o": 116.5,
   "h": 116.5,
   "l": 115.0,
   "c": 115.0,
   "v": 12456001
  },
  {
   "time": "2026-05-21",
   "o": 115.0,
   "h": 115.0,
   "l": 113.0,
   "c": 113.5,
   "v": 16190499
  },
  {
   "time": "2026-05-22",
   "o": 113.5,
   "h": 113.5,
   "l": 111.5,
   "c": 112.0,
   "v": 17068730
  },
  {
   "time": "2026-05-25",
   "o": 112.0,
   "h": 112.5,
   "l": 111.0,
   "c": 111.5,
   "v": 14606395
  },
  {
   "time": "2026-05-26",
   "o": 111.5,
   "h": 112.0,
   "l": 110.0,
   "c": 110.5,
   "v": 22455627
  },
  {
   "time": "2026-05-27",
   "o": 111.0,
   "h": 111.5,
   "l": 110.0,
   "c": 110.0,
   "v": 15348191
  },
  {
   "time": "2026-05-28",
   "o": 110.0,
   "h": 112.5,
   "l": 110.0,
   "c": 111.0,
   "v": 20049099
  },
  {
   "time": "2026-05-29",
   "o": 111.5,
   "h": 112.5,
   "l": 111.5,
   "c": 111.5,
   "v": 21115271
  },
  {
   "time": "2026-06-01",
   "o": 112.5,
   "h": 115.0,
   "l": 112.0,
   "c": 114.0,
   "v": 15371222
  },
  {
   "time": "2026-06-02",
   "o": 114.0,
   "h": 115.5,
   "l": 114.0,
   "c": 115.5,
   "v": 18399448
  },
  {
   "time": "2026-06-03",
   "o": 115.5,
   "h": 116.5,
   "l": 114.5,
   "c": 116.0,
   "v": 13001421
  },
  {
   "time": "2026-06-04",
   "o": 116.0,
   "h": 117.0,
   "l": 115.5,
   "c": 116.0,
   "v": 7875810
  },
  {
   "time": "2026-06-05",
   "o": 116.0,
   "h": 116.5,
   "l": 115.0,
   "c": 116.0,
   "v": 7011302
  },
  {
   "time": "2026-06-08",
   "o": 115.0,
   "h": 116.0,
   "l": 114.0,
   "c": 115.0,
   "v": 17725512
  },
  {
   "time": "2026-06-09",
   "o": 115.0,
   "h": 117.0,
   "l": 115.0,
   "c": 117.0,
   "v": 18611504
  },
  {
   "time": "2026-06-10",
   "o": 116.5,
   "h": 118.0,
   "l": 116.0,
   "c": 118.0,
   "v": 12131355
  }
 ],
 "sr": {
  "price": 118.0,
  "resistance": [],
  "support": [
   110.9,
   109.46
  ],
  "strong_support": 96.16
 },
 "spark": [
  108.0,
  109.5,
  110.0,
  109.5,
  109.0,
  109.0,
  109.5,
  109.0,
  109.0,
  109.5,
  109.0,
  109.0,
  109.5,
  109.5,
  109.5,
  109.5,
  110.0,
  110.0,
  110.0,
  110.0,
  110.0,
  110.0,
  112.5,
  113.5,
  113.5,
  113.0,
  112.0,
  113.0,
  112.0,
  111.0,
  112.0,
  111.5,
  110.5,
  110.5,
  110.0,
  110.0,
  110.0,
  110.0,
  110.0,
  112.0,
  115.0,
  114.5,
  114.0,
  116.5,
  115.0,
  113.5,
  112.0,
  111.5,
  110.5,
  110.0,
  111.0,
  111.5,
  114.0,
  115.5,
  116.0,
  116.0,
  116.0,
  115.0,
  117.0,
  118.0
 ],
 "spark_start": "2026-03-16",
 "spark_end": "2026-06-10",
 "fundamental": null,
 "levels": null,
 "generated_for": "detail"
}