{
 "stock": "6152",
 "name": "百一",
 "price": 15.2,
 "change_pct": 0.0,
 "ohlc": [
  {
   "time": "2026-03-13",
   "o": 18.8,
   "h": 19.5,
   "l": 18.5,
   "c": 19.1,
   "v": 5104247
  },
  {
   "time": "2026-03-16",
   "o": 18.9,
   "h": 19.3,
   "l": 18.3,
   "c": 18.8,
   "v": 4889120
  },
  {
   "time": "2026-03-17",
   "o": 18.9,
   "h": 20.0,
   "l": 18.7,
   "c": 19.25,
   "v": 6389021
  },
  {
   "time": "2026-03-18",
   "o": 19.8,
   "h": 19.8,
   "l": 18.6,
   "c": 19.0,
   "v": 5666682
  },
  {
   "time": "2026-03-19",
   "o": 18.5,
   "h": 20.9,
   "l": 18.3,
   "c": 20.35,
   "v": 9797955
  },
  {
   "time": "2026-03-20",
   "o": 21.45,
   "h": 21.45,
   "l": 19.0,
   "c": 19.05,
   "v": 8702285
  },
  {
   "time": "2026-03-23",
   "o": 18.2,
   "h": 19.95,
   "l": 17.9,
   "c": 18.65,
   "v": 5257254
  },
  {
   "time": "2026-03-24",
   "o": 18.9,
   "h": 19.4,
   "l": 17.5,
   "c": 18.2,
   "v": 5850324
  },
  {
   "time": "2026-03-25",
   "o": 18.5,
   "h": 19.5,
   "l": 18.05,
   "c": 18.75,
   "v": 5901286
  },
  {
   "time": "2026-03-26",
   "o": 19.1,
   "h": 19.4,
   "l": 18.5,
   "c": 18.5,
   "v": 5483866
  },
  {
   "time": "2026-03-27",
   "o": 18.5,
   "h": 18.9,
   "l": 17.4,
   "c": 18.0,
   "v": 5635129
  },
  {
   "time": "2026-03-30",
   "o": 17.5,
   "h": 17.5,
   "l": 16.2,
   "c": 16.45,
   "v": 4680117
  },
  {
   "time": "2026-03-31",
   "o": 16.2,
   "h": 16.65,
   "l": 15.5,
   "c": 15.7,
   "v": 4075465
  },
  {
   "time": "2026-04-01",
   "o": 16.35,
   "h": 16.5,
   "l": 15.75,
   "c": 16.05,
   "v": 3947250
  },
  {
   "time": "2026-04-02",
   "o": 16.05,
   "h": 17.0,
   "l": 15.55,
   "c": 16.5,
   "v": 4302100
  },
  {
   "time": "2026-04-07",
   "o": 16.8,
   "h": 16.9,
   "l": 15.65,
   "c": 16.2,
   "v": 3532564
  },
  {
   "time": "2026-04-08",
   "o": 16.9,
   "h": 17.5,
   "l": 15.95,
   "c": 16.6,
   "v": 3656279
  },
  {
   "time": "2026-04-09",
   "o": 16.65,
   "h": 18.25,
   "l": 16.15,
   "c": 18.25,
   "v": 7824367
  },
  {
   "time": "2026-04-10",
   "o": 18.5,
   "h": 18.7,
   "l": 17.6,
   "c": 17.9,
   "v": 7196230
  },
  {
   "time": "2026-04-13",
   "o": 17.5,
   "h": 18.55,
   "l": 17.2,
   "c": 18.0,
   "v": 7016710
  },
  {
   "time": "2026-04-14",
   "o": 17.55,
   "h": 18.5,
   "l": 17.5,
   "c": 17.95,
   "v": 5834651
  },
  {
   "time": "2026-04-15",
   "o": 18.2,
   "h": 18.3,
   "l": 17.5,
   "c": 17.6,
   "v": 4347500
  },
  {
   "time": "2026-04-16",
   "o": 17.8,
   "h": 18.2,
   "l": 17.6,
   "c": 17.7,
   "v": 2796780
  },
  {
   "time": "2026-04-17",
   "o": 17.8,
   "h": 18.2,
   "l": 17.2,
   "c": 17.4,
   "v": 5303500
  },
  {
   "time": "2026-04-20",
   "o": 17.35,
   "h": 17.35,
   "l": 16.05,
   "c": 16.15,
   "v": 4710375
  },
  {
   "time": "2026-04-21",
   "o": 16.15,
   "h": 16.65,
   "l": 15.9,
   "c": 16.2,
   "v": 4713111
  },
  {
   "time": "2026-04-22",
   "o": 16.3,
   "h": 16.3,
   "l": 15.7,
   "c": 15.75,
   "v": 3230577
  },
  {
   "time": "2026-04-23",
   "o": 15.85,
   "h": 15.85,
   "l": 14.3,
   "c": 14.85,
   "v": 5252402
  },
  {
   "time": "2026-04-24",
   "o": 15.15,
   "h": 15.15,
   "l": 13.9,
   "c": 14.15,
   "v": 4391400
  },
  {
   "time": "2026-04-27",
   "o": 14.15,
   "h": 14.15,
   "l": 13.4,
   "c": 13.6,
   "v": 3163818
  },
  {
   "time": "2026-04-28",
   "o": 13.6,
   "h": 14.25,
   "l": 13.45,
   "c": 14.0,
   "v": 1444660
  },
  {
   "time": "2026-04-29",
   "o": 14.0,
   "h": 14.25,
   "l": 13.8,
   "c": 13.9,
   "v": 868505
  },
  {
   "time": "2026-04-30",
   "o": 13.9,
   "h": 13.9,
   "l": 13.4,
   "c": 13.5,
   "v": 1023228
  },
  {
   "time": "2026-05-04",
   "o": 13.85,
   "h": 14.4,
   "l": 13.6,
   "c": 14.05,
   "v": 1064061
  },
  {
   "time": "2026-05-05",
   "o": 13.75,
   "h": 14.05,
   "l": 13.75,
   "c": 14.0,
   "v": 746200
  },
  {
   "time": "2026-05-06",
   "o": 14.0,
   "h": 14.05,
   "l": 13.65,
   "c": 13.7,
   "v": 1221204
  },
  {
   "time": "2026-05-07",
   "o": 13.7,
   "h": 14.1,
   "l": 13.7,
   "c": 13.95,
   "v": 1278292
  },
  {
   "time": "2026-05-08",
   "o": 13.8,
   "h": 14.3,
   "l": 13.45,
   "c": 13.5,
   "v": 1782247
  },
  {
   "time": "2026-05-11",
   "o": 14.65,
   "h": 14.85,
   "l": 14.6,
   "c": 14.85,
   "v": 1239651
  },
  {
   "time": "2026-05-12",
   "o": 16.2,
   "h": 16.3,
   "l": 15.7,
   "c": 16.05,
   "v": 6843478
  },
  {
   "time": "2026-05-13",
   "o": 15.7,
   "h": 16.1,
   "l": 15.2,
   "c": 15.5,
   "v": 2040280
  },
  {
   "time": "2026-05-14",
   "o": 15.75,
   "h": 16.5,
   "l": 15.2,
   "c": 15.8,
   "v": 2576114
  },
  {
   "time": "2026-05-15",
   "o": 15.8,
   "h": 15.8,
   "l": 14.7,
   "c": 14.8,
   "v": 2101906
  },
  {
   "time": "2026-05-18",
   "o": 14.3,
   "h": 15.7,
   "l": 14.25,
   "c": 15.6,
   "v": 1511894
  },
  {
   "time": "2026-05-19",
   "o": 15.5,
   "h": 15.75,
   "l": 14.9,
   "c": 15.15,
   "v": 1248192
  },
  {
   "time": "2026-05-20",
   "o": 14.9,
   "h": 15.4,
   "l": 14.9,
   "c": 14.95,
   "v": 628327
  },
  {
   "time": "2026-05-21",
   "o": 15.05,
   "h": 15.45,
   "l": 15.0,
   "c": 15.4,
   "v": 1204500
  },
  {
   "time": "2026-05-22",
   "o": 15.6,
   "h": 16.2,
   "l": 15.45,
   "c": 16.1,
   "v": 3010514
  },
  {
   "time": "2026-05-25",
   "o": 16.5,
   "h": 16.5,
   "l": 15.4,
   "c": 15.65,
   "v": 2816424
  },
  {
   "time": "2026-05-26",
   "o": 16.15,
   "h": 16.15,
   "l": 15.1,
   "c": 15.15,
   "v": 2045076
  },
  {
   "time": "2026-05-27",
   "o": 15.3,
   "h": 15.3,
   "l": 14.9,
   "c": 14.95,
   "v": 1491235
  },
  {
   "time": "2026-05-28",
   "o": 15.0,
   "h": 15.35,
   "l": 14.95,
   "c": 15.0,
   "v": 1602100
  },
  {
   "time": "2026-05-29",
   "o": 15.3,
   "h": 15.45,
   "l": 15.0,
   "c": 15.3,
   "v": 1000001
  },
  {
   "time": "2026-06-01",
   "o": 15.1,
   "h": 15.3,
   "l": 14.85,
   "c": 15.1,
   "v": 1797174
  },
  {
   "time": "2026-06-02",
   "o": 15.25,
   "h": 15.5,
   "l": 14.8,
   "c": 15.3,
   "v": 1869894
  },
  {
   "time": "2026-06-03",
   "o": 15.75,
   "h": 16.25,
   "l": 15.3,
   "c": 15.8,
   "v": 3422121
  },
  {
   "time": "2026-06-04",
   "o": 15.8,
   "h": 15.8,
   "l": 14.95,
   "c": 15.25,
   "v": 1968110
  },
  {
   "time": "2026-06-05",
   "o": 15.3,
   "h": 15.8,
   "l": 14.7,
   "c": 15.8,
   "v": 2121276
  },
  {
   "time": "2026-06-08",
   "o": 14.75,
   "h": 15.35,
   "l": 14.55,
   "c": 15.2,
   "v": 1657061
  },
  {
   "time": "2026-06-09",
   "o": 15.45,
   "h": 15.45,
   "l": 15.0,
   "c": 15.2,
   "v": 1418719
  }
 ],
 "sr": {
  "price": 15.2,
  "resistance": [
   15.8,
   16.15
  ],
  "support": [
   14.8,
   14.75
  ],
  "strong_support": 7.66
 },
 "spark": [
  19.1,
  18.8,
  19.25,
  19.0,
  20.35,
  19.05,
  18.65,
  18.2,
  18.75,
  18.5,
  18.0,
  16.45,
  15.7,
  16.05,
  16.5,
  16.2,
  16.6,
  18.25,
  17.9,
  18.0,
  17.95,
  17.6,
  17.7,
  17.4,
  16.15,
  16.2,
  15.75,
  14.85,
  14.15,
  13.6,
  14.0,
  13.9,
  13.5,
  14.05,
  14.0,
  13.7,
  13.95,
  13.5,
  14.85,
  16.05,
  15.5,
  15.8,
  14.8,
  15.6,
  15.15,
  14.95,
  15.4,
  16.1,
  15.65,
  15.15,
  14.95,
  15.0,
  15.3,
  15.1,
  15.3,
  15.8,
  15.25,
  15.8,
  15.2,
  15.2
 ],
 "spark_start": "2026-03-13",
 "spark_end": "2026-06-09",
 "fundamental": {
  "rev_yoy": 116.9,
  "rev_accel": false,
  "stale": false,
  "source": "twse_revenue"
 },
 "levels": null,
 "generated_for": "detail"
}